{
  "players": [
    {
      "id": 1,
      "name": "Randi M",
      "character": "Rhubarb",
      "email": "randiemail@gmail.com",
      "password": "RandiPassword"
    },
    {
      "id": 2,
      "name": "Spenser W",
      "character": "Dungeon Master",
      "email": "spenseremail@gmail.com",
      "password": "SpenserPassword"
    },
    {
      "id": 3,
      "name": "Janey R",
      "character": "Theo",
      "email": "janeyemail@gmail.com",
      "password": "JaneyPassword"
    },
    {
      "id": 4,
      "name": "Tyler E",
      "character": "Devil Woman",
      "email": "tyleremail@gmail.com",
      "password": "TylerPassword"
    }
  ]
}
